nastja/__init__.py
nastja/io.py
nastja-0.0.4.dist-info/LICENSE
nastja-0.0.4.dist-info/METADATA
nastja-0.0.4.dist-info/WHEEL
nastja-0.0.4.dist-info/pbr.json
nastja-0.0.4.dist-info/top_level.txt
nastja-0.0.4.dist-info/RECORD
