Metadata-Version: 2.1
Name: nastja
Version: 0.0.4
Summary: Python module to access the NAStJA output files
Home-page: https://gitlab.com/nastja/nastjapy/
Author: Marco Berghoff
Author-email: marco.berghoff@kit.edu
License: UNKNOWN
Project-URL: Bug Tracker, https://gitlab.com/nastja/nastjapy/issues
Project-URL: Documentation, https://nastja.gitlab.io/nastjapy
Project-URL: Source Code, https://gitlab.com/nastja/nastjapy
Platform: UNKNOWN
Classifier: Programming Language :: Python :: 3
Classifier: License :: OSI Approved :: MIT License
Classifier: Operating System :: OS Independent
Requires-Python: >=3.6
License-File: LICENSE
Requires-Dist: numpy
